LICENSE
README.md
setup.py
pyortho/__init__.py
pyortho/divne.py
pyortho/drr3d.py
pyortho/focus.py
pyortho/localortho.py
pyortho/localsimi.py
pyortho/snr.py
pyortho.egg-info/PKG-INFO
pyortho.egg-info/SOURCES.txt
pyortho.egg-info/dependency_links.txt
pyortho.egg-info/not-zip-safe
pyortho.egg-info/requires.txt
pyortho.egg-info/top_level.txt
pyortho/src/orthocfuns.c